multi_agent_llm/__init__.py
multi_agent_llm/agent_class.py
multi_agent_llm/llm.py
multi_agent_llm/agents/__init__.py
multi_agent_llm/agents/base.py
multi_agent_llm/agents/iteration_of_thought.py
generalist_multi_agent_llm-0.1.2.dist-info/LICENSE
generalist_multi_agent_llm-0.1.2.dist-info/METADATA
generalist_multi_agent_llm-0.1.2.dist-info/WHEEL
generalist_multi_agent_llm-0.1.2.dist-info/top_level.txt
generalist_multi_agent_llm-0.1.2.dist-info/RECORD
