Metadata-Version: 2.1
Name: generalist-multi-agent-llm
Version: 0.1.2
Summary: An LLM Multi-Agent framework.
Author: Agnostiq Inc.
Author-email: contact@agnostiq.ai
Classifier: Development Status :: 3 - Alpha
Classifier: Intended Audience :: Developers
Classifier: Intended Audience :: Education
Classifier: Intended Audience :: Science/Research
Classifier: Programming Language :: Python :: 3 :: Only
Classifier: Operating System :: OS Independent
Classifier: Topic :: Scientific/Engineering :: Artificial Intelligence
Requires-Python: >=3.7
License-File: LICENSE
Requires-Dist: openai (>=1.46.0)
Requires-Dist: pydantic (==2.9.2)
Requires-Dist: tenacity (==9.0.0)
